<cr>
<coord lat="17.18974354772762" lon="48.03951893823742"/><coord lat="17.18983219078494" lon="48.03944798640803"/><coord lat="17.19059994941723" lon="48.03930213990657"/><coord lat="17.19106665564836" lon="48.03919307519747"/><coord lat="17.19144050931677" lon="48.03904070807935"/><coord lat="17.19244407121959" lon="48.03867779638771"/><coord lat="17.19312147101241" lon="48.03840782145635"/><coord lat="17.19325913962632" lon="48.03834513355036"/><coord lat="17.1935537511069" lon="48.03863626275283"/><coord lat="17.19377134283168" lon="48.03853927132305"/><coord lat="17.19398806498723" lon="48.03844267193005"/><coord lat="17.19420450686841" lon="48.03834614503371"/><coord lat="17.19433834326931" lon="48.03828654256116"/><coord lat="17.19439905860273" lon="48.03854305656297"/><coord lat="17.19439204006544" lon="48.0386955080411"/><coord lat="17.1941894493076" lon="48.0389031414056"/><coord lat="17.19417480676847" lon="48.03891815492172"/><coord lat="17.1943963645552" lon="48.03880904555316"/><coord lat="17.1946591334539" lon="48.0385946119596"/><coord lat="17.19543784254951" lon="48.03784229591724"/><coord lat="17.19522131443007" lon="48.03764454139821"/><coord lat="17.1952719910902" lon="48.03760122059128"/><coord lat="17.19554943486738" lon="48.03736065829783"/><coord lat="17.19576131869682" lon="48.0374767575354"/><coord lat="17.19608372584894" lon="48.03714449659126"/><coord lat="17.19616940895735" lon="48.03693632515591"/><coord lat="17.19653970709388" lon="48.0360372545814"/><coord lat="17.19656578788151" lon="48.03591319800617"/><coord lat="17.19665605599114" lon="48.03548308945047"/><coord lat="17.19646473729351" lon="48.03457275586022"/><coord lat="17.19645511903179" lon="48.03452710120105"/><coord lat="17.19644895030072" lon="48.03449713167404"/><coord lat="17.19644882992648" lon="48.03449703376186"/><coord lat="17.19605447311002" lon="48.03479418074399"/><coord lat="17.19602740237892" lon="48.0348409860775"/><coord lat="17.19599322866888" lon="48.03490014803026"/><coord lat="17.19575720620946" lon="48.03533257046016"/><coord lat="17.19563565337173" lon="48.03560494078103"/><coord lat="17.19562858991865" lon="48.03562064423262"/><coord lat="17.19553437910323" lon="48.03591925457847"/><coord lat="17.19553358858579" lon="48.03593086075424"/><coord lat="17.19552578761585" lon="48.03604078111629"/><coord lat="17.19552107056229" lon="48.03606513768669"/><coord lat="17.19548208547559" lon="48.03626921729079"/><coord lat="17.19547342930949" lon="48.03630008798923"/><coord lat="17.19542026611267" lon="48.03648992850228"/><coord lat="17.19536279279911" lon="48.03688355836989"/><coord lat="17.19533400359089" lon="48.03707982737907"/><coord lat="17.19509887405686" lon="48.03726267939084"/><coord lat="17.19509216184504" lon="48.03726792191577"/><coord lat="17.19497320783343" lon="48.03736052014721"/><coord lat="17.19484189749511" lon="48.03741767182088"/><coord lat="17.19473524860627" lon="48.0374640080634"/><coord lat="17.19471879416519" lon="48.03747130720557"/><coord lat="17.19456071403138" lon="48.03754075772289"/><coord lat="17.19446331509501" lon="48.03757117656951"/><coord lat="17.1943794968891" lon="48.03761353395609"/><coord lat="17.19435558193964" lon="48.03762566411913"/><coord lat="17.19426534706767" lon="48.0376613542318"/><coord lat="17.19408096516062" lon="48.03773545352762"/><coord lat="17.19405112672017" lon="48.03774845100101"/><coord lat="17.19390538764173" lon="48.0378119523119"/><coord lat="17.19373447058251" lon="48.03788072003305"/><coord lat="17.19362951411967" lon="48.0379229209966"/><coord lat="17.19361723774297" lon="48.03792932690992"/><coord lat="17.19351624015561" lon="48.03798200733295"/><coord lat="17.19338905847431" lon="48.03804847254798"/><coord lat="17.19333569046158" lon="48.03807642724306"/><coord lat="17.19317173085425" lon="48.0381626541766"/><coord lat="17.19303790253816" lon="48.03823301073542"/><coord lat="17.19291331069984" lon="48.03829838485732"/><coord lat="17.19282844865156" lon="48.03833506676701"/><coord lat="17.19265051934324" lon="48.03841194847152"/><coord lat="17.19242217208958" lon="48.03851056487608"/><coord lat="17.19218893889911" lon="48.03857785228687"/><coord lat="17.19201400637057" lon="48.03862836193436"/><coord lat="17.19191105404912" lon="48.03865804375459"/><coord lat="17.19181477441361" lon="48.03868726967244"/><coord lat="17.19160661949091" lon="48.03876437669148"/><coord lat="17.19143894894314" lon="48.03883932430304"/><coord lat="17.19124849262816" lon="48.03890171369183"/><coord lat="17.19104306678732" lon="48.03895875794391"/><coord lat="17.19087186047056" lon="48.03899785694228"/><coord lat="17.1907283806551" lon="48.03903448309544"/><coord lat="17.190573117638" lon="48.03907329853669"/><coord lat="17.19051401837379" lon="48.03908369492424"/><coord lat="17.19033466882898" lon="48.03912947588365"/><coord lat="17.19015531748755" lon="48.03917525740297"/><coord lat="17.19003720519738" lon="48.0392053641565"/><coord lat="17.18999390280743" lon="48.03921646085572"/><coord lat="17.1898871488157" lon="48.03923820257105"/><coord lat="17.1897940734708" lon="48.03925408570576"/><coord lat="17.18977591133238" lon="48.0392583766259"/><coord lat="17.18963862629906" lon="48.03928511498453"/><coord lat="17.1896018474747" lon="48.03929674082362"/><coord lat="17.18950282797757" lon="48.03932804036105"/><coord lat="17.18943155833789" lon="48.03933870097518"/><coord lat="17.18922688079365" lon="48.03935466876797"/><coord lat="17.18921262992" lon="48.03935443332038"/><coord lat="17.18886643268423" lon="48.03934795670973"/><coord lat="17.18846284657653" lon="48.03934042058389"/><coord lat="17.18847095387197" lon="48.03935470360461"/><coord lat="17.18778777431862" lon="48.03934950453748"/><coord lat="17.18777209602195" lon="48.03932187727693"/><coord lat="17.18768624852183" lon="48.03931827108255"/><coord lat="17.18759280666428" lon="48.03931858160934"/><coord lat="17.18745164090897" lon="48.03930908441539"/><coord lat="17.18742304663516" lon="48.03930833542717"/><coord lat="17.18735722258271" lon="48.03931592801713"/><coord lat="17.18725208555848" lon="48.03932864699927"/><coord lat="17.18715718393862" lon="48.03933871118595"/><coord lat="17.18706165529466" lon="48.03935207704269"/><coord lat="17.18695171497861" lon="48.03936447347682"/><coord lat="17.18691603389554" lon="48.03936785743428"/><coord lat="17.186767197426" lon="48.03938170258721"/><coord lat="17.18667126723513" lon="48.03939504140445"/><coord lat="17.18658569282283" lon="48.03940491998318"/><coord lat="17.18656852062788" lon="48.03940530078322"/><coord lat="17.18641480540802" lon="48.03940851415885"/><coord lat="17.18623404460994" lon="48.03941234738538"/><coord lat="17.18605557810905" lon="48.03941615538516"/><coord lat="17.18567448222282" lon="48.03942042526973"/><coord lat="17.18566797931849" lon="48.0394323700131"/><coord lat="17.18563601905729" lon="48.03946492598672"/><coord lat="17.18559478997901" lon="48.03948736793182"/><coord lat="17.18549640469247" lon="48.03949999737777"/><coord lat="17.18548116297705" lon="48.03953159950902"/><coord lat="17.18529155826498" lon="48.03963055072287"/><coord lat="17.18548890106491" lon="48.03997254977495"/><coord lat="17.18572771638654" lon="48.04018420696451"/><coord lat="17.18578692614356" lon="48.04020012103989"/><coord lat="17.1857869459065" lon="48.04020016608652"/><coord lat="17.18592890667084" lon="48.0402384172667"/><coord lat="17.18609858046171" lon="48.04029249537536"/><coord lat="17.18628127623094" lon="48.04032078640142"/><coord lat="17.18657237889202" lon="48.04028569334621"/><coord lat="17.1872100327251" lon="48.04030970795869"/><coord lat="17.18785075340653" lon="48.04034115643514"/><coord lat="17.18824560968631" lon="48.04034404001199"/><coord lat="17.18855576381794" lon="48.0402824770222"/><coord lat="17.18889911159761" lon="48.04020082196542"/><coord lat="17.18933380187202" lon="48.0401338063538"/><coord lat="17.18945355358762" lon="48.04011438462143"/><coord lat="17.18963671648077" lon="48.04008458711936"/><coord lat="17.18976460783114" lon="48.03999991661632"/><coord lat="17.18978357306343" lon="48.0398379634929"/><coord lat="17.18974354772762" lon="48.03951893823742"/><coord lat="17.18974354772762" lon="48.03951893823742"/>
</cr>